{
  "_fv": 13,
  "_type": "recipe",
  "definition": {
    "recipeType": "Crafting",
    "xpReward": 0.0,
    "cookingTime": 200,
    "recipeRetstackSize": 4,
    "group": "",
    "recipeShapeless": false,
    "recipeSlots": [
      {
        "value": "CUSTOM:Siding3jm"
      },
      {
        "value": "CUSTOM:Siding3jm"
      },
      {
        "value": "Items.DYE#0"
      },
      {
        "value": "CUSTOM:Siding3jm"
      },
      {
        "value": "CUSTOM:Siding3jm"
      },
      {
        "value": "Blocks.PLANKS"
      },
      {
        "value": ""
      },
      {
        "value": ""
      },
      {
        "value": ""
      }
    ],
    "recipeReturnStack": {
      "value": "CUSTOM:Siding3jmTrimD"
    },
    "name": "siding_3jm_trim_d_crafting_alt",
    "namespace": "mod"
  }
}